ddutils/__init__.py
ddutils/annotation_helpers.py
ddutils/class_helpers.py
ddutils/convertors.py
ddutils/datetime_helpers.py
ddutils/function_exceptions_extractor.py
ddutils/function_helpers.py
ddutils/module_getter.py
ddutils/object_getter.py
ddutils/py.typed
ddutils/safe_decorators.py
ddutils/scoped_registry.py
ddutils/sequence_helpers.py
ddutils-0.1.4.dist-info/METADATA
ddutils-0.1.4.dist-info/WHEEL
ddutils-0.1.4.dist-info/licenses/LICENSE
ddutils-0.1.4.dist-info/RECORD
