Metadata-Version: 2.4
Name: ddutils
Version: 0.1.4
Summary: Domain Driven Utils Library
License: MIT
License-File: LICENSE
Keywords: python,ddutils
Author: davyddd
Requires-Python: >=3.9,<3.15
Classifier: License :: OSI Approved :: MIT License
Classifier: Programming Language :: Python :: 3
Classifier: Programming Language :: Python :: 3.9
Classifier: Programming Language :: Python :: 3.10
Classifier: Programming Language :: Python :: 3.11
Classifier: Programming Language :: Python :: 3.12
Classifier: Programming Language :: Python :: 3.13
Classifier: Programming Language :: Python :: 3.14
Project-URL: Repository, https://github.com/davyddd/ddutils
